tencent_cloud_search_mcp/__init__.py
tencent_cloud_search_mcp/cli.py
tencent_cloud_search_mcp/config.py
tencent_cloud_search_mcp/server.py
tencent_cloud_search_mcp-0.1.9.dist-info/METADATA
tencent_cloud_search_mcp-0.1.9.dist-info/WHEEL
tencent_cloud_search_mcp-0.1.9.dist-info/entry_points.txt
tencent_cloud_search_mcp-0.1.9.dist-info/licenses/LICENSE
tencent_cloud_search_mcp-0.1.9.dist-info/RECORD
