Metadata-Version: 2.4
Name: tencent-cloud-search-mcp
Version: 0.1.9
Summary: 腾讯云联网搜索API的MCP服务器
Project-URL: Homepage, https://github.com/yourusername/tencent-cloud-search-mcp
Project-URL: Repository, https://github.com/yourusername/tencent-cloud-search-mcp
Project-URL: Issues, https://github.com/yourusername/tencent-cloud-search-mcp/issues
Author-email: jiny <jiny@haiweikexin.com>
License: MIT
License-File: LICENSE
Classifier: Development Status :: 3 - Alpha
Classifier: Intended Audience :: Developers
Classifier: License :: OSI Approved :: MIT License
Classifier: Operating System :: OS Independent
Classifier: Programming Language :: Python :: 3
Classifier: Programming Language :: Python :: 3.10
Classifier: Programming Language :: Python :: 3.11
Classifier: Programming Language :: Python :: 3.12
Requires-Python: >=3.10
Requires-Dist: mcp>=1.0.0
Requires-Dist: tencentcloud-sdk-python-wsa>=3.0.1443
Provides-Extra: dev
Requires-Dist: black>=23.0.0; extra == 'dev'
